django_form_builder/__init__.py
django_form_builder/admin.py
django_form_builder/apps.py
django_form_builder/captcha.py
django_form_builder/dynamic_fields.py
django_form_builder/enc.py
django_form_builder/exceptions.py
django_form_builder/forms.py
django_form_builder/formsets.py
django_form_builder/models.py
django_form_builder/settings.py
django_form_builder/utils.py
django_form_builder/views.py
django_form_builder/widgets.py
django_form_builder/data/__init__.py
django_form_builder/data/audio_captcha/__init__.py
django_form_builder/data/audio_captcha/en/__init__.py
django_form_builder/data/audio_captcha/en/0/__init__.py
django_form_builder/data/audio_captcha/en/0/default.wav
django_form_builder/data/audio_captcha/en/1/__init__.py
django_form_builder/data/audio_captcha/en/1/default.wav
django_form_builder/data/audio_captcha/en/2/__init__.py
django_form_builder/data/audio_captcha/en/2/default.wav
django_form_builder/data/audio_captcha/en/3/__init__.py
django_form_builder/data/audio_captcha/en/3/default.wav
django_form_builder/data/audio_captcha/en/4/__init__.py
django_form_builder/data/audio_captcha/en/4/default.wav
django_form_builder/data/audio_captcha/en/5/__init__.py
django_form_builder/data/audio_captcha/en/5/default.wav
django_form_builder/data/audio_captcha/en/6/__init__.py
django_form_builder/data/audio_captcha/en/6/default.wav
django_form_builder/data/audio_captcha/en/7/__init__.py
django_form_builder/data/audio_captcha/en/7/default.wav
django_form_builder/data/audio_captcha/en/8/__init__.py
django_form_builder/data/audio_captcha/en/8/default.wav
django_form_builder/data/audio_captcha/en/9/__init__.py
django_form_builder/data/audio_captcha/en/9/default.wav
django_form_builder/data/audio_captcha/en/A/__init__.py
django_form_builder/data/audio_captcha/en/A/default.wav
django_form_builder/data/audio_captcha/en/B/__init__.py
django_form_builder/data/audio_captcha/en/B/default.wav
django_form_builder/data/audio_captcha/en/C/__init__.py
django_form_builder-1.2.2.dist-info/licenses/AUTHORS
django_form_builder-1.2.2.dist-info/licenses/LICENSE
django_form_builder-1.2.2.dist-info/METADATA
django_form_builder-1.2.2.dist-info/WHEEL
django_form_builder-1.2.2.dist-info/top_level.txt
django_form_builder-1.2.2.dist-info/RECORD
